reminix_llamaindex/__init__.py
reminix_llamaindex/agent_adapter.py
reminix_llamaindex/py.typed
reminix_llamaindex-0.0.18.dist-info/METADATA
reminix_llamaindex-0.0.18.dist-info/WHEEL
reminix_llamaindex-0.0.18.dist-info/licenses/LICENSE
reminix_llamaindex-0.0.18.dist-info/RECORD
