Metadata-Version: 2.4
Name: reminix-llamaindex
Version: 0.0.18
Summary: Reminix adapter for LlamaIndex - serve agents as REST APIs
Project-URL: Homepage, https://reminix.com
Project-URL: Documentation, https://reminix.com/docs
Project-URL: Repository, https://github.com/reminix-ai/runtime-python
Project-URL: Changelog, https://github.com/reminix-ai/runtime-python/blob/main/CHANGELOG.md
Project-URL: Bug Tracker, https://github.com/reminix-ai/runtime-python/issues
Author-email: Reminix Team <team@reminix.com>
License-Expression: Apache-2.0
License-File: LICENSE
Keywords: agents,ai,llama-index,llamaindex,llm,rag,reminix
Classifier: Development Status :: 4 - Beta
Classifier: Intended Audience :: Developers
Classifier: License :: OSI Approved :: Apache Software License
Classifier: Programming Language :: Python :: 3
Classifier: Programming Language :: Python :: 3.10
Classifier: Programming Language :: Python :: 3.11
Classifier: Programming Language :: Python :: 3.12
Classifier: Topic :: Scientific/Engineering :: Artificial Intelligence
Requires-Python: >=3.10
Requires-Dist: llama-index>=0.14.0
Requires-Dist: reminix-runtime~=0.0.18
Provides-Extra: dev
Requires-Dist: pytest-asyncio>=0.24.0; extra == 'dev'
Requires-Dist: pytest>=8.0.0; extra == 'dev'
